LICENSE
MANIFEST.in
setup.py
flask_msearch/__init__.py
flask_msearch/backends.py
flask_msearch/clickhouse_backend.py
flask_msearch/elasticsearch_backend.py
flask_msearch/signal.py
flask_msearch/simple_backend.py
flask_msearch/whoosh_backend.py
flask_msearch.egg-info/PKG-INFO
flask_msearch.egg-info/SOURCES.txt
flask_msearch.egg-info/dependency_links.txt
flask_msearch.egg-info/not-zip-safe
flask_msearch.egg-info/requires.txt
flask_msearch.egg-info/top_level.txt