Metadata-Version: 1.1
Name: flask-msearch
Version: 0.2.8
Summary: full text search with whoosh for flask
Home-page: https://github.com/honmaple/flask-msearch
Author: honmaple
Author-email: mail@honmaple.com
License: BSD
Platform: any
Classifier: Environment :: Web Environment
Classifier: Intended Audience :: Developers
Classifier: License :: OSI Approved :: BSD License
Classifier: Operating System :: OS Independent
Classifier: Programming Language :: Python
Classifier: Topic :: Internet :: WWW/HTTP :: Dynamic Content
Classifier: Topic :: Software Development :: Libraries :: Python Modules
